MANIFEST.in
README.rst
setup.py
docs/HISTORY.txt
docs/LICENSE.GPL
docs/LICENSE.txt
simplelayout/__init__.py
simplelayout.types.flowplayerblock.egg-info/PKG-INFO
simplelayout.types.flowplayerblock.egg-info/SOURCES.txt
simplelayout.types.flowplayerblock.egg-info/dependency_links.txt
simplelayout.types.flowplayerblock.egg-info/entry_points.txt
simplelayout.types.flowplayerblock.egg-info/namespace_packages.txt
simplelayout.types.flowplayerblock.egg-info/not-zip-safe
simplelayout.types.flowplayerblock.egg-info/requires.txt
simplelayout.types.flowplayerblock.egg-info/top_level.txt
simplelayout/types/__init__.py
simplelayout/types/flowplayerblock/__init__.py
simplelayout/types/flowplayerblock/configure.zcml
simplelayout/types/flowplayerblock/flowplayer.pt
simplelayout/types/flowplayerblock/flowplayer.py
simplelayout/types/flowplayerblock/sl-movie.gif
simplelayout/types/flowplayerblock/testing.py
simplelayout/types/flowplayerblock/js/simplelayout.flowplayer.js
simplelayout/types/flowplayerblock/profiles/default/jsregistry.xml
simplelayout/types/flowplayerblock/profiles/default/metadata.xml
simplelayout/types/flowplayerblock/profiles/default/types/File.xml
simplelayout/types/flowplayerblock/profiles/plone3/actionicons.xml
simplelayout/types/flowplayerblock/profiles/plone3/metadata.xml
simplelayout/types/flowplayerblock/profiles/plone3/types.xml
simplelayout/types/flowplayerblock/profiles/plone3/types/File.xml
simplelayout/types/flowplayerblock/tests/__init__.py
simplelayout/types/flowplayerblock/tests/test_flowplayerblock.py
simplelayout/types/flowplayerblock/upgrades/__init__.py
simplelayout/types/flowplayerblock/upgrades/configure.zcml
simplelayout/types/flowplayerblock/upgrades/to1000.py
simplelayout/types/flowplayerblock/upgrades/to1001.py
simplelayout/types/flowplayerblock/upgrades/to1002.py
simplelayout/types/flowplayerblock/upgrades/to1100.py
simplelayout/types/flowplayerblock/upgrades/profiles/1000/jsregistry.xml
simplelayout/types/flowplayerblock/upgrades/profiles/1001/types/File.xml
simplelayout/types/flowplayerblock/upgrades/profiles/1002/types/File.xml
simplelayout/types/flowplayerblock/upgrades/profiles/1100/types/File.xml