Metadata-Version: 1.1
Name: simplelayout.types.flowplayerblock
Version: 1.1.0
Summary: Flow-player support for simplelayout file blocks.
Home-page: https://github.com/4teamwork/simplelayout.types.flowplayerblock
Author: 4teamwork GmbH
Author-email: mailto:info@4teamwork.ch
License: GPL2
Platform: UNKNOWN
Classifier: Framework :: Plone
Classifier: Framework :: Plone :: 4.1
Classifier: Framework :: Plone :: 4.2
Classifier: Programming Language :: Python
Classifier: Topic :: Software Development :: Libraries :: Python Modules
